<?xml version="1.0"?><h:html xmlns="http://www.w3.org/2002/xforms" xmlns:ev="http://www.w3.org/2001/xml-events" xmlns:h="http://www.w3.org/1999/xhtml" xmlns:jr="http://openrosa.org/javarosa" xmlns:odk="http://www.opendatakit.org/xforms" xmlns:orx="http://openrosa.org/xforms" xmlns:xsd="http://www.w3.org/2001/XMLSchema"><h:head><h:title>Form R - Objeccoes e Correcoes</h:title><model odk:xforms-version="1.0.0"><submission action="http://cavateco.terrafirma.co.mz:8080/wcs_nampula/submission" method="post"/><itext><translation default="true()" lang="default"><text id="/data/g1/logo:label"><value form="image">jr://images/terrafirma_wcs.jpg</value></text></translation></itext><instance><data id="form_r_correcoes" version="2022012801"><start/><deviceid/><external_id/><project/><my_form_name/><g1><logo/><cavateco/></g1><intronote/><searchtext/><enum_name_id/><enum_name/><date/><prov_id/><dist_id/><post_id/><assoc_id/><assoc_name/><parcel_id/><parcel_id_check/><outcome/><party_id/><party_id_check/><issues/><parcel_id_new/><new_family_name/><new_name/><new_other_name/><new_gender/><new_birthdate/><new_id_document/><new_id_number/><new_limits/><new_limits_image/><end/><meta><instanceID/><instanceName/></meta></data></instance><instance id="enum_names_wcs_nampula" src="jr://file-csv/enum_names_wcs_nampula.csv"/><instance id="assoc_names_wcs_nampula" src="jr://file-csv/assoc_names_wcs_nampula.csv"/><bind jr:preload="timestamp" jr:preloadParams="start" nodeset="/data/start" type="dateTime"/><bind jr:preload="property" jr:preloadParams="deviceid" nodeset="/data/deviceid" type="string"/><bind calculate="&quot;fixed&quot;" nodeset="/data/external_id" type="string"/><bind calculate="&quot;WCS - Futura Azul&quot;" nodeset="/data/project" type="string"/><bind calculate="&quot;Formulário R - Objecções e Correcções&quot;" nodeset="/data/my_form_name" type="string"/><bind nodeset="/data/g1/logo" readonly="true()" type="string"/><bind nodeset="/data/g1/cavateco" readonly="true()" type="string"/><bind nodeset="/data/intronote" readonly="true()" type="string"/><bind nodeset="/data/searchtext" required="true()" type="string"/><bind nodeset="/data/enum_name_id" required="true()" type="string"/><bind calculate="pulldata('enum_names_wcs_nampula', 'enumerator_name', 'name_id_key',  /data/enum_name_id )" nodeset="/data/enum_name" type="string"/><bind constraint=". &lt;= today()" nodeset="/data/date" required="true()" type="date"/><bind nodeset="/data/prov_id" required="true()" type="string"/><bind nodeset="/data/dist_id" required="true()" type="string"/><bind nodeset="/data/post_id" required="true()" type="string"/><bind nodeset="/data/assoc_id" required="true()" type="string"/><bind calculate="pulldata('assoc_names_wcs_nampula', 'assoc_name', 'assoc_id_key',  /data/assoc_id )" nodeset="/data/assoc_name" type="string"/><bind constraint="regex(.,'[0-9]{6}')" nodeset="/data/parcel_id" required="true()" type="string"/><bind constraint=".= /data/parcel_id " jr:constraintMsg="O número da parcela/registo que reentrou não corresponde à sua primeira entrada. Faça a favor de verificar de novo." nodeset="/data/parcel_id_check" required="true()" type="string"/><bind nodeset="/data/outcome" required="true()" type="string"/><bind nodeset="/data/party_id" required="true()" type="string"/><bind constraint=".= /data/party_id " jr:constraintMsg="O número do titular que reentrou não corresponde à sua primeira entrada. Faça a favor de verificar de novo." nodeset="/data/party_id_check" required="true()" type="string"/><bind nodeset="/data/issues" relevant=" /data/outcome ='change'" required="true()" type="string"/><bind nodeset="/data/parcel_id_new" relevant="selected( /data/issues , 'parcel')" required="true()" type="string"/><bind constraint="regex(., &quot;^[a-zA-Z0-9. _-éáíóãõúçâôàèê]{1,75}$&quot;)" jr:constraintMsg="Resposta invalida - O campo do apelido não pode incluir um novo paragrafo. Faça a favor de eliminar qualquer linha adicional." nodeset="/data/new_family_name" relevant="selected( /data/issues , 'family_name')" required="true()" type="string"/><bind constraint="regex(., &quot;^[a-zA-Z0-9. _-éáíóãõúçâôàèê]{1,75}$&quot;)" jr:constraintMsg="Resposta invalida - O campo do nome não pode incluir um novo paragrafo. Faça a favor de eliminar qualquer linha adicional." nodeset="/data/new_name" relevant="selected( /data/issues , 'given_name')" required="true()" type="string"/><bind constraint="regex(., &quot;^[a-zA-Z0-9. _-éáíóãõúçâôàèê]{1,75}$&quot;)" jr:constraintMsg="Resposta invalida - O campo do outro nome não pode incluir um novo paragrafo. Faça a favor de eliminar qualquer linha adicional." nodeset="/data/new_other_name" relevant="selected( /data/issues , 'other_name')" required="true()" type="string"/><bind nodeset="/data/new_gender" relevant="selected( /data/issues , 'gender')" required="true()" type="string"/><bind nodeset="/data/new_birthdate" relevant="selected( /data/issues , 'birthdate')" required="true()" type="date"/><bind nodeset="/data/new_id_document" relevant="selected( /data/issues , 'id_document')" required="true()" type="string"/><bind constraint="regex(., &quot;^[a-zA-Z0-9. _-]{1,25}$&quot;)" jr:constraintMsg="Resposta invalida - O campo de numero do documento não pode incluir um novo paragrafo. Faça a favor de eliminar qualquer linha adicional." nodeset="/data/new_id_number" relevant="selected( /data/issues , 'id_number')" required="true()" type="string"/><bind calculate=" /data/parcel_id " nodeset="/data/new_limits" relevant="selected( /data/issues , 'reconfig')" required="true()" type="string"/><bind nodeset="/data/new_limits_image" relevant="selected( /data/issues , 'reconfig')" required="true()" type="binary"/><bind jr:preload="timestamp" jr:preloadParams="end" nodeset="/data/end" type="dateTime"/><bind jr:preload="uid" nodeset="/data/meta/instanceID" readonly="true()" type="string"/><bind calculate="concat('OC','_', /data/party_id ,'_', /data/parcel_id )" nodeset="/data/meta/instanceName" type="string"/></model></h:head><h:body><group appearance="field-list" ref="/data/g1"><input ref="/data/g1/logo"><label ref="jr:itext('/data/g1/logo:label')"/></input><input ref="/data/g1/cavateco"><label>&lt;br/&gt; &lt;h1&gt;Cadeia de Valor de Terra Comunitária&lt;/h1&gt;&lt;br/&gt; &lt;h2&gt;<output value=" /data/project "/>&lt;/h2&gt;&lt;span style=&quot;color:#57b055&quot;&gt;<output value=" /data/my_form_name "/>&lt;/span&gt; &lt;br/&gt;</label></input></group><input ref="/data/intronote"><label>&lt;span style=&quot;color:#FF0000&quot;&gt;<output value=" /data/project "/>&lt;/span&gt;&lt;br/&gt; &lt;span style=&quot;color:#57b055&quot;&gt;<output value=" /data/my_form_name "/>&lt;/span&gt; &lt;br/&gt;

O técnico pode usar o formulário &lt;br/&gt; &lt;span style=&quot;color:#57b055&quot;&gt;depois de conclusão da publicação do edital&lt;/span&gt;.

O formulário é usado para reportar:

- a necessidade de mudar a configuração dos limites de parcelas

ou

- mudanças na informação publicada no edital, relacionada aos titulares

ou

- para confirmar a informação publicada no edital, relacionada aos titulares

&lt;span style=&quot;color:#FF0000&quot;&gt;Se houver mais de um titular para uma parcela, o formulário deve ser preenchido uma vez para cada titular&lt;/span&gt; &lt;br/&gt; &lt;br/&gt;

Por favor deslizar para a frente para continuar.</label></input><input ref="/data/searchtext"><label>Digite a primeira letra do seu nome para filtrar a lista de enumeradores já registadas:</label></input><select1 appearance="search('enum_names_wcs_nampula', 'startswith', 'enumerator_name',  /data/searchtext )" ref="/data/enum_name_id"><label>Selecionar o seu nome:</label><hint>&lt;h3&gt;Se o seu nome &lt;span style="color:#FF6347"&gt;não aparece&lt;/span&gt; em baixo, quer dizer que ainda não fez o registo dos seus dados, ou que houve problema na actualização do sistema. Não será possível continuar. Deve fazer o seu registo de pessoa através do 'Formulário 1', e depois actualizar os dados, e voltar a repetir o registo de ponto mais tarde. Pode fechar o Formulário sem gravar.</hint><item><label>enumerator_name</label><value>name_id_key</value></item></select1><input appearance="no-calendar" ref="/data/date"><label>Data do registo:</label></input><select1 appearance="minimal" ref="/data/prov_id"><label>Selecionar a província:</label><item><label>Cabo Delgado</label><value>P02</value></item><item><label>Gaza</label><value>P09</value></item><item><label>Inhambane</label><value>P08</value></item><item><label>Manica</label><value>P06</value></item><item><label>Maputo</label><value>P10</value></item><item><label>Nampula</label><value>P03</value></item><item><label>Niassa</label><value>P01</value></item><item><label>Sofala</label><value>P07</value></item><item><label>Tete</label><value>P05</value></item><item><label>Zambezia</label><value>P04</value></item></select1><input appearance="minimal" ref="/data/dist_id" query="instance('districts')/root/item[prov_id= /data/prov_id ]"><label>Selecionar o distrito:</label></input><input appearance="minimal" ref="/data/post_id" query="instance('posts')/root/item[dist_id= /data/dist_id ]"><label>Selecionar o posto administrativo:</label></input><select1 appearance="search('assoc_names_wcs_nampula', 'matches', 'post_id',  /data/post_id )" ref="/data/assoc_id"><label>Selecionar a associação</label><item><label>assoc_name</label><value>assoc_id_key</value></item></select1><input appearance="numbers" ref="/data/parcel_id"><label>Qual é o numero da parcela/registo?</label></input><input appearance="numbers" ref="/data/parcel_id_check"><label>Por favor, re-digite o número da parcela/registo como confirmação:</label></input><input ref="/data/outcome" query="instance('outcomes')/root/item[external_id= /data/external_id ]"><label>Por favor, selecione o resultado para esta parcela</label></input><input appearance="numbers" ref="/data/party_id"><label>Qual é o numero (Interno id) do titular ou co-titular?</label><hint>Isto é o 'Interno id'</hint></input><input appearance="numbers" ref="/data/party_id_check"><label>Por favor, re-digite o número (Interno id) do titular ou co-titular como confirmação:</label></input><select ref="/data/issues"><label>Indique toda a informação que precisa ser alterada:</label><item><label>Mudar o numero da parcela</label><value>parcel</value></item><item><label>Mudar o apelido da pessoa</label><value>family_name</value></item><item><label>Mudar o nome da pessoa</label><value>given_name</value></item><item><label>Mudar o outro nome  da pessoa</label><value>other_name</value></item><item><label>Mudar o género da pessoa:</label><value>gender</value></item><item><label>Mudar o tipo de documento de identificação</label><value>id_document</value></item><item><label>Mudar o numero de documento</label><value>id_number</value></item><item><label>Mudar o data de nascimento</label><value>birthdate</value></item><item><label>Reconfigurar os limites da parcela</label><value>reconfig</value></item></select><input appearance="numbers" ref="/data/parcel_id_new"><label>Mudar numero da parcela/registo para:</label></input><input ref="/data/new_family_name"><label>Mudar apelido da pessoa para:</label></input><input ref="/data/new_name"><label>Mudar nome da pessoa para:</label></input><input ref="/data/new_other_name"><label>Mudar outro nome da pessoa para:</label></input><input appearance="minimal" ref="/data/new_gender" query="instance('genders')/root/item[external_id= /data/external_id ]"><label>Mudar género da pessoa para:</label></input><input appearance="no-calendar" ref="/data/new_birthdate"><label>Mudar data de nascimento da pessoa para:</label></input><input appearance="minimal" ref="/data/new_id_document" query="instance('documents')/root/item[external_id= /data/external_id ]"><label>Mudar o tipo de documento de identificação:</label></input><input ref="/data/new_id_number"><label>Mudar o numero de documento para:</label></input><upload mediatype="image/*" ref="/data/new_limits_image"><label>Tire uma fotografia da parcela no mapa, mostrando claramente a mudança nos limites</label></upload></h:body></h:html>